{
  "type": "FeatureCollection",
  "features": [
    {
      "type": "Feature",
      "properties": {
        "興甲地区": 0
      },
      "geometry": {
        "type": "Polygon",
        "coordinates": [
          [
            [
              142.7381766,
              46.6838871
            ],
            [
              143.0978191,
              46.9096845
            ],
            [
              143.1113188,
              46.9018804
            ],
            [
              143.116511,
              46.8891076
            ],
            [
              143.1346965,
              46.8799406
            ],
            [
              143.1559888,
              46.8767701
            ],
            [
              143.1591042,
              46.8680146
            ],
            [
              143.161181,
              46.863518
            ],
            [
              143.165681,
              46.8547603
            ],
            [
              143.1783648,
              46.8493892
            ],
            [
              143.195629,
              46.83897
            ],
            [
              143.217971,
              46.8278539
            ],
            [
              143.2352349,
              46.8202105
            ],
            [
              143.2657012,
              46.8104807
            ],
            [
              143.2941364,
              46.8014442
            ],
            [
              143.3266337,
              46.7937969
            ],
            [
              143.3560844,
              46.7924063
            ],
            [
              143.3977217,
              46.7951874
            ],
            [
              143.4210791,
              46.8028346
            ],
            [
              143.4241258,
              46.8097856
            ],
            [
              143.4292035,
              46.8174307
            ],
            [
              143.4251413,
              46.823685
            ],
            [
              143.4231102,
              46.8341072
            ],
            [
              143.4292035,
              46.8438328
            ],
            [
              143.4352967,
              46.8466112
            ],
            [
              143.4505299,
              46.8438328
            ],
            [
              143.4596697,
              46.8341072
            ],
            [
              143.4728718,
              46.828549
            ],
            [
              143.478965,
              46.8174307
            ],
            [
              143.4779495,
              46.8028346
            ],
            [
              143.4881049,
              46.785453
            ],
            [
              143.4881049,
              46.7784988
            ],
            [
              143.4891205,
              46.7722393
            ],
            [
              143.4870894,
              46.7618051
            ],
            [
              143.4931826,
              46.7506731
            ],
            [
              143.501307,
              46.7290982
            ],
            [
              143.5084158,
              46.7214406
            ],
            [
              143.5134935,
              46.7158707
            ],
            [
              143.5094313,
              46.7026399
            ],
            [
              143.4972448,
              46.6928888
            ],
            [
              143.4992759,
              46.6712908
            ],
            [
              143.5063847,
              46.6441069
            ],
            [
              143.5185712,
              46.6259767
            ],
            [
              143.5134934,
              46.6078404
            ],
            [
              143.5134934,
              46.5827186
            ],
            [
              143.5266955,
              46.5589818
            ],
            [
              143.5287266,
              46.5450142
            ],
            [
              143.5307577,
              46.5317415
            ],
            [
              143.5338043,
              46.5156703
            ],
            [
              143.5409131,
              46.5065845
            ],
            [
              143.5368509,
              46.4974971
            ],
            [
              143.5439597,
              46.4919042
            ],
            [
              143.5429442,
              46.4793179
            ],
            [
              143.5541668,
              46.4637886
            ],
            [
              143.5572134,
              46.4609904
            ],
            [
              143.5582289,
              46.4504961
            ],
            [
              143.5693101,
              46.4350428
            ],
            [
              143.5703218,
              46.4337555
            ],
            [
              143.5696992,
              46.4304299
            ],
            [
              143.5686096,
              46.4284451
            ],
            [
              143.5690766,
              46.426514
            ],
            [
              143.5640957,
              46.42072
            ],
            [
              143.5704154,
              46.4084986
            ],
            [
              143.5836175,
              46.395893
            ],
            [
              143.5988506,
              46.3867872
            ],
            [
              143.6120527,
              46.3853861
            ],
            [
              143.6150993,
              46.3783804
            ],
            [
              143.6140838,
              46.3706731
            ],
            [
              143.6008817,
              46.3685709
            ],
            [
              143.5852191,
              46.3583622
            ],
            [
              143.5740481,
              46.3520539
            ],
            [
              143.5649083,
              46.3415386
            ],
            [
              143.5618616,
              46.3198006
            ],
            [
              143.5638927,
              46.2980539
            ],
            [
              143.548161,
              46.2982615
            ],
            [
              143.5251424,
              46.2866384
            ],
            [
              143.5127477,
              46.2621605
            ],
            [
              143.5083211,
              46.2315478
            ],
            [
              143.5065504,
              46.2131719
            ],
            [
              143.4914997,
              46.2064326
            ],
            [
              143.4799904,
              46.200918
            ],
            [
              143.4658251,
              46.1929514
            ],
            [
              143.4587424,
              46.1788539
            ],
            [
              143.4587424,
              46.159234
            ],
            [
              143.4578571,
              46.1285639
            ],
            [
              143.4648493,
              46.0952327
            ],
            [
              143.4285507,
              46.0596124
            ],
            [
              143.4276653,
              46.0460953
            ],
            [
              143.4170413,
              46.0208954
            ],
            [
              143.4090733,
              46.0233544
            ],
            [
              143.3993347,
              46.0946187
            ],
            [
              143.408188,
              46.1148754
            ],
            [
              143.410844,
              46.1222396
            ],
            [
              143.408188,
              46.1412593
            ],
            [
              143.405532,
              46.1572062
            ],
            [
              143.421468,
              46.1749877
            ],
            [
              143.4223533,
              46.2093083
            ],
            [
              143.4152706,
              46.2252355
            ],
            [
              143.376316,
              46.3139755
            ],
            [
              143.37366,
              46.3323176
            ],
            [
              143.3568386,
              46.3579861
            ],
            [
              143.3373613,
              46.3793674
            ],
            [
              143.341788,
              46.3885282
            ],
            [
              143.3400173,
              46.3958558
            ],
            [
              143.3329347,
              46.4007403
            ],
            [
              143.33382,
              46.4062348
            ],
            [
              143.33382,
              46.4160015
            ],
            [
              143.328508,
              46.4294279
            ],
            [
              143.3391075,
              46.4398174
            ],
            [
              143.3391075,
              46.4581173
            ],
            [
              143.3267128,
              46.4806786
            ],
            [
              143.2895288,
              46.5190723
            ],
            [
              143.2009955,
              46.5854356
            ],
            [
              143.1407929,
              46.6097687
            ],
            [
              143.1115769,
              46.5994284
            ],
            [
              143.0832462,
              46.5945618
            ],
            [
              143.0673102,
              46.5945618
            ],
            [
              143.0531449,
              46.5982118
            ],
            [
              143.0071076,
              46.6079441
            ],
            [
              142.9823183,
              46.6067276
            ],
            [
              142.9513316,
              46.6128096
            ],
            [
              142.9168036,
              46.6225392
            ],
            [
              142.8689957,
              46.6249713
            ],
            [
              142.830041,
              46.6158503
            ],
            [
              142.7893157,
              46.6030782
            ],
            [
              142.7680677,
              46.6091605
            ],
            [
              142.7689531,
              46.6219312
            ],
            [
              142.7600997,
              46.6346988
            ],
            [
              142.7609851,
              46.6419932
            ],
            [
              142.7494757,
              46.6553638
            ],
            [
              142.7494757,
              46.6681236
            ],
            [
              142.7381766,
              46.6838871
            ]
          ]
        ]
      }
    },
    {
      "type": "Feature",
      "properties": {
        "": "",
        "羽洟縣": 0
      },
      "geometry": {
        "type": "Polygon",
        "coordinates": [
          [
            [
              141.9616313,
              46.9166746
            ],
            [
              143.1027644,
              46.9123931
            ],
            [
              142.737428,
              46.6833867
            ],
            [
              142.7198215,
              46.7467622
            ],
            [
              142.6670018,
              46.7346964
            ],
            [
              142.5789689,
              46.7256453
            ],
            [
              142.5129443,
              46.6803669
            ],
            [
              142.4249114,
              46.592721
            ],
            [
              142.2708539,
              46.3046107
            ],
            [
              142.2444441,
              46.2498496
            ],
            [
              142.240042,
              46.1676055
            ],
            [
              142.1960256,
              46.0669175
            ],
            [
              142.1828207,
              46.033314
            ],
            [
              142.1650252,
              46.0133307
            ],
            [
              142.1160742,
              46.0003661
            ],
            [
              142.0991895,
              45.9782823
            ],
            [
              142.0895318,
              45.9655935
            ],
            [
              142.0861389,
              45.9496719
            ],
            [
              142.0815829,
              45.9048215
            ],
            [
              142.0354914,
              45.9219426
            ],
            [
              142.0116733,
              45.9520045
            ],
            [
              141.9715418,
              46.0119193
            ],
            [
              141.9407543,
              46.0299723
            ],
            [
              141.9343917,
              46.0265103
            ],
            [
              141.9338935,
              46.0263101
            ],
            [
              141.9324895,
              46.0263632
            ],
            [
              141.9358392,
              46.0331839
            ],
            [
              141.9151559,
              46.0473765
            ],
            [
              141.9143205,
              46.0638635
            ],
            [
              141.9275254,
              46.131013
            ],
            [
              141.8791073,
              46.2802793
            ],
            [
              141.8879106,
              46.3289314
            ],
            [
              141.8312199,
              46.4604537
            ],
            [
              141.8080654,
              46.5465163
            ],
            [
              141.8219581,
              46.5661534
            ],
            [
              141.8126963,
              46.5979824
            ],
            [
              141.843569,
              46.618131
            ],
            [
              141.8394926,
              46.6743269
            ],
            [
              141.8967139,
              46.7045201
            ],
            [
              141.9616313,
              46.9166746
            ]
          ]
        ]
      }
    },
    {
      "type": "Feature",
      "properties": {
        "ハガニバ縣": 0
      },
      "geometry": {
        "type": "Polygon",
        "coordinates": [
          [
            [
              142.0488133,
              47.1813256
            ],
            [
              142.5044551,
              47.1767559
            ],
            [
              142.5094038,
              47.4083511
            ],
            [
              142.8855026,
              47.394953
            ],
            [
              142.9398184,
              47.3372178
            ],
            [
              142.9745787,
              47.2809314
            ],
            [
              142.999322,
              47.2305495
            ],
            [
              143.0240653,
              47.1397412
            ],
            [
              143.014168,
              47.0925942
            ],
            [
              143.0389114,
              47.0150479
            ],
            [
              143.0785007,
              46.9475245
            ],
            [
              143.0981204,
              46.911989
            ],
            [
              141.9913024,
              46.9193873
            ],
            [
              142.0343316,
              47.0082994
            ],
            [
              142.0491776,
              47.0588923
            ],
            [
              142.0541263,
              47.1397412
            ],
            [
              142.0488133,
              47.1813256
            ]
          ]
        ]
      }
    },
    {
      "type": "Feature",
      "properties": {
        "サハリンスク縣": 0
      },
      "geometry": {
        "type": "Polygon",
        "coordinates": [
          [
            [
              142.1686419,
              47.9788053
            ],
            [
              142.5137537,
              47.9106686
            ],
            [
              142.5181439,
              47.8283578
            ],
            [
              142.5365322,
              47.7455071
            ],
            [
              142.5768735,
              47.6463122
            ],
            [
              142.6300911,
              47.5521134
            ],
            [
              142.7365262,
              47.4712366
            ],
            [
              142.8667494,
              47.3959797
            ],
            [
              142.5095846,
              47.4075003
            ],
            [
              142.5047693,
              47.1764286
            ],
            [
              142.0463004,
              47.1813256
            ],
            [
              141.9981326,
              47.2504402
            ],
            [
              141.9382628,
              47.2910639
            ],
            [
              141.9914804,
              47.3271477
            ],
            [
              141.9715238,
              47.3992414
            ],
            [
              141.9382628,
              47.48922
            ],
            [
              141.9382628,
              47.5835318
            ],
            [
              141.9914804,
              47.6418304
            ],
            [
              142.0446979,
              47.7671757
            ],
            [
              142.1178721,
              47.8788366
            ],
            [
              142.1577853,
              47.9368054
            ],
            [
              142.1686419,
              47.9788053
            ]
          ]
        ]
      }
    },
    {
      "type": "Feature",
      "properties": {
        "サハミガ地区": 0
      },
      "geometry": {
        "type": "Polygon",
        "coordinates": [
          [
            [
              141.9682328,
              48.8700096
            ],
            [
              142.9719992,
              48.9924331
            ],
            [
              142.9719992,
              48.9116431
            ],
            [
              142.9251322,
              48.8345786
            ],
            [
              142.8255397,
              48.6916962
            ],
            [
              142.0741108,
              48.429343
            ],
            [
              141.9702161,
              48.5445289
            ],
            [
              141.9233491,
              48.5987984
            ],
            [
              141.8706236,
              48.7071626
            ],
            [
              141.8589069,
              48.7689804
            ],
            [
              141.8823404,
              48.8191514
            ],
            [
              141.9682328,
              48.8700096
            ]
          ]
        ]
      }
    },
    {
      "type": "Feature",
      "properties": {
        "サハリナシャスク": 0
      },
      "geometry": {
        "type": "Polygon",
        "coordinates": [
          [
            [
              142.4242577,
              48.5516435
            ],
            [
              142.3131675,
              47.9504309
            ],
            [
              142.5139192,
              47.9106329
            ],
            [
              142.56016,
              48.1113999
            ],
            [
              142.6528042,
              48.3105675
            ],
            [
              142.8260288,
              48.6918279
            ],
            [
              142.4242577,
              48.5516435
            ]
          ]
        ]
      }
    },
    {
      "type": "Feature",
      "properties": {
        "トイラジ・コハバ": 0
      },
      "geometry": {
        "type": "Polygon",
        "coordinates": [
          [
            [
              142.0743757,
              48.4291673
            ],
            [
              142.4239701,
              48.5512955
            ],
            [
              142.3085274,
              47.9432999
            ],
            [
              142.1853891,
              47.9831054
            ],
            [
              142.1768968,
              48.1051735
            ],
            [
              142.181143,
              48.2071476
            ],
            [
              142.1471738,
              48.229781
            ],
            [
              142.1556661,
              48.2637123
            ],
            [
              142.1429277,
              48.3089191
            ],
            [
              142.0743757,
              48.4291673
            ]
          ]
        ]
      }
    },
    {
      "type": "Feature",
      "properties": {
        "トジャン縣": 0
      },
      "geometry": {
        "type": "Polygon",
        "coordinates": [
          [
            [
              142.1322842,
              49.6272481
            ],
            [
              143.3686684,
              49.3009128
            ],
            [
              143.2346478,
              49.2723868
            ],
            [
              143.0983855,
              49.2166293
            ],
            [
              142.9811509,
              49.1300632
            ],
            [
              142.9430013,
              49.0521176
            ],
            [
              142.9430013,
              49.0231066
            ],
            [
              142.9475793,
              49.0010869
            ],
            [
              142.9723148,
              48.9926802
            ],
            [
              141.9755401,
              48.8685123
            ],
            [
              141.9907137,
              48.953279
            ],
            [
              141.9907137,
              49.1521632
            ],
            [
              142.1121024,
              49.2116733
            ],
            [
              142.0741684,
              49.2711119
            ],
            [
              142.0589949,
              49.3502521
            ],
            [
              142.1424496,
              49.4785838
            ],
            [
              142.1322842,
              49.6272481
            ]
          ]
        ]
      }
    },
    {
      "type": "Feature",
      "properties": {
        "アイスポーク首都直轄市": 0
      },
      "geometry": {
        "type": "Polygon",
        "coordinates": [
          [
            [
              142.9508379,
              49.4113677
            ],
            [
              144.1595677,
              49.5645832
            ],
            [
              144.1986653,
              49.4732079
            ],
            [
              144.2299434,
              49.361295
            ],
            [
              144.2690409,
              49.2593345
            ],
            [
              144.3394166,
              49.1367033
            ],
            [
              144.3706947,
              49.070151
            ],
            [
              144.4254313,
              49.0188963
            ],
            [
              144.5661826,
              48.9470508
            ],
            [
              144.6678363,
              48.9008098
            ],
            [
              144.6834753,
              48.8390884
            ],
            [
              144.6834753,
              48.7515195
            ],
            [
              144.7147534,
              48.6637977
            ],
            [
              144.6287387,
              48.7824436
            ],
            [
              144.5896411,
              48.8339416
            ],
            [
              144.542724,
              48.9162282
            ],
            [
              144.4801679,
              48.9881181
            ],
            [
              144.3237776,
              49.070151
            ],
            [
              144.1908458,
              49.1776141
            ],
            [
              144.0813725,
              49.2491268
            ],
            [
              143.7607724,
              49.3154389
            ],
            [
              143.7216748,
              49.3511084
            ],
            [
              143.6200211,
              49.3511084
            ],
            [
              143.5340064,
              49.3154389
            ],
            [
              143.3686684,
              49.3018327
            ],
            [
              142.9508379,
              49.4113677
            ]
          ]
        ]
      }
    },
    {
      "type": "Feature",
      "properties": {
        "サバリャク縣": 0
      },
      "geometry": {
        "type": "Polygon",
        "coordinates": [
          [
            [
              142.1330283,
              49.6260628
            ],
            [
              143.8181628,
              50.3144884
            ],
            [
              143.8181628,
              50.225613
            ],
            [
              143.8930349,
              50.0885577
            ],
            [
              143.9572109,
              50.0473645
            ],
            [
              143.999995,
              49.8615569
            ],
            [
              144.0855631,
              49.7718382
            ],
            [
              144.0855631,
              49.6957924
            ],
            [
              144.1663465,
              49.5672083
            ],
            [
              142.9527035,
              49.4110418
            ],
            [
              142.1330283,
              49.6260628
            ]
          ]
        ]
      }
    },
    {
      "type": "Feature",
      "properties": {
        "ユジノ・サハリンスク縣": ""
      },
      "geometry": {
        "type": "Polygon",
        "coordinates": [
          [
            [
              142.81822,
              49.9060627
            ],
            [
              142.4707751,
              50.9772014
            ],
            [
              142.1114668,
              50.8734488
            ],
            [
              142.0680298,
              50.566909
            ],
            [
              142.0573349,
              50.4282892
            ],
            [
              142.1791298,
              50.3055581
            ],
            [
              142.1565396,
              50.1128925
            ],
            [
              142.1698059,
              49.9433404
            ],
            [
              142.1351131,
              49.7888949
            ],
            [
              142.1342646,
              49.6254466
            ],
            [
              142.81822,
              49.9060627
            ]
          ]
        ]
      }
    },
    {
      "type": "Feature",
      "properties": {
        "ポルキンスカヤ特別市": 0
      },
      "geometry": {
        "type": "Polygon",
        "coordinates": [
          [
            [
              142.112919,
              50.8722304
            ],
            [
              142.4763042,
              50.9754993
            ],
            [
              142.8191268,
              49.9085446
            ],
            [
              143.8096536,
              50.3080415
            ],
            [
              143.4868163,
              51.2485295
            ],
            [
              143.50135,
              51.3088001
            ],
            [
              142.7982167,
              51.2670663
            ],
            [
              142.7294346,
              51.6453512
            ],
            [
              142.0104743,
              51.5272627
            ],
            [
              142.191435,
              51.2993347
            ],
            [
              142.2339719,
              51.2220038
            ],
            [
              142.2505835,
              51.0238029
            ],
            [
              142.112919,
              50.8722304
            ]
          ]
        ]
      }
    },
    {
      "type": "Feature",
      "properties": {
        "ガーガスク縣": 0
      },
      "geometry": {
        "type": "Polygon",
        "coordinates": [
          [
            [
              141.8049644,
              52.6042035
            ],
            [
              143.136308,
              52.2573712
            ],
            [
              143.2356029,
              52.3741017
            ],
            [
              143.3348977,
              52.5416531
            ],
            [
              143.3309131,
              52.8439741
            ],
            [
              143.283147,
              53.0150379
            ],
            [
              143.2368885,
              53.2675558
            ],
            [
              143.111337,
              53.4760748
            ],
            [
              142.7620428,
              53.4654688
            ],
            [
              142.7184594,
              53.6091756
            ],
            [
              142.7662911,
              53.7039299
            ],
            [
              142.7596569,
              53.7756268
            ],
            [
              142.7279548,
              53.8525063
            ],
            [
              142.6771534,
              53.8304042
            ],
            [
              142.5940054,
              53.7057761
            ],
            [
              142.4717964,
              53.6650655
            ],
            [
              142.425968,
              53.6107234
            ],
            [
              141.9218557,
              53.4427278
            ],
            [
              141.6850756,
              53.3972091
            ],
            [
              141.7843705,
              53.2786324
            ],
            [
              141.8301989,
              53.1826181
            ],
            [
              141.9218557,
              53.0542639
            ],
            [
              141.8760273,
              52.9255263
            ],
            [
              141.8049644,
              52.6042035
            ]
          ]
        ]
      }
    },
    {
      "type": "Feature",
      "properties": {
        "カマハリド地区": 0
      },
      "geometry": {
        "type": "Polygon",
        "coordinates": [
          [
            [
              142.5172499,
              52.4209675
            ],
            [
              142.7231706,
              51.6461673
            ],
            [
              142.0078349,
              51.5272627
            ],
            [
              141.8899557,
              51.5888382
            ],
            [
              141.8099655,
              51.6741808
            ],
            [
              141.6727221,
              51.745605
            ],
            [
              141.7335807,
              51.7215247
            ],
            [
              141.7671565,
              51.7152844
            ],
            [
              141.805937,
              51.7215188
            ],
            [
              141.8267534,
              51.7797262
            ],
            [
              141.7601086,
              51.8538113
            ],
            [
              141.6149853,
              51.8868238
            ],
            [
              141.6684518,
              51.9574834
            ],
            [
              141.6302615,
              52.0984689
            ],
            [
              141.6684518,
              52.1406779
            ],
            [
              141.6455376,
              52.2249761
            ],
            [
              141.6684518,
              52.2857587
            ],
            [
              141.6455376,
              52.3417919
            ],
            [
              141.7906608,
              52.5001675
            ],
            [
              141.8288511,
              52.6023428
            ],
            [
              142.5172499,
              52.4209675
            ]
          ]
        ]
      }
    },
    {
      "type": "Feature",
      "properties": {
        "ヨバハマリ縣": 0
      },
      "geometry": {
        "type": "Polygon",
        "coordinates": [
          [
            [
              142.518601,
              52.4195453
            ],
            [
              142.6775085,
              51.834891
            ],
            [
              142.7498172,
              51.5468509
            ],
            [
              142.8002797,
              51.2697055
            ],
            [
              143.499349,
              51.3081217
            ],
            [
              143.2549309,
              51.8492251
            ],
            [
              143.155636,
              51.9010963
            ],
            [
              143.147998,
              51.9999571
            ],
            [
              143.147998,
              52.2531706
            ],
            [
              142.518601,
              52.4195453
            ]
          ]
        ]
      }
    },
    {
      "type": "Feature",
      "properties": {
        "オハ省": 0
      },
      "geometry": {
        "type": "Polygon",
        "coordinates": [
          [
            [
              142.6787099,
              53.8320906
            ],
            [
              142.7280586,
              53.8525559
            ],
            [
              142.7584965,
              53.7778216
            ],
            [
              142.7668149,
              53.7035362
            ],
            [
              142.7172869,
              53.6080622
            ],
            [
              142.7604493,
              53.466658
            ],
            [
              143.1123003,
              53.4766405
            ],
            [
              143.0942771,
              53.4983212
            ],
            [
              143.0547217,
              53.5756832
            ],
            [
              142.9747362,
              53.6904733
            ],
            [
              142.8902311,
              53.7887837
            ],
            [
              142.8786644,
              53.8657912
            ],
            [
              142.8892706,
              53.9277429
            ],
            [
              142.9072701,
              54.0033865
            ],
            [
              142.988685,
              54.054818
            ],
            [
              142.9811556,
              54.1019623
            ],
            [
              142.7889296,
              54.2946088
            ],
            [
              142.7189796,
              54.4279064
            ],
            [
              142.675602,
              54.4195316
            ],
            [
              142.6644182,
              54.3819173
            ],
            [
              142.5850211,
              54.3402621
            ],
            [
              142.380721,
              54.2759829
            ],
            [
              142.2693664,
              54.313264
            ],
            [
              142.3846126,
              54.2182215
            ],
            [
              142.3849019,
              54.1648368
            ],
            [
              142.523421,
              54.0770728
            ],
            [
              142.6332812,
              53.9891153
            ],
            [
              142.7016631,
              53.9259205
            ],
            [
              142.6787099,
              53.8320906
            ]
          ]
        ]
      }
    }
  ]
}